pawel_replenishment.py
pawel_replenishment-0.0.1.dist-info/LICENSE
pawel_replenishment-0.0.1.dist-info/WHEEL
pawel_replenishment-0.0.1.dist-info/METADATA
pawel_replenishment-0.0.1.dist-info/RECORD
